syft_rds/__init__.py
syft_rds/cli.py
syft_rds/orchestra.py
syft_rds/assets/adjectives.txt
syft_rds/assets/data_access_template.py.jinja
syft_rds/assets/nouns.txt
syft_rds/assets/css/fonts.css
syft_rds/assets/css/model_repr.css
syft_rds/assets/css/style.css
syft_rds/assets/css/tabulator_pysyft.min.css
syft_rds/assets/jinja/model_repr.jinja2
syft_rds/assets/jinja/model_repr_file_section.jinja2
syft_rds/assets/jinja/syft_exception.jinja2
syft_rds/assets/jinja/table.jinja2
syft_rds/assets/js/table.js
syft_rds/assets/js/tabulator.min.js
syft_rds/assets/svg/arrow.svg
syft_rds/assets/svg/clipboard.svg
syft_rds/assets/svg/copy.svg
syft_rds/assets/svg/folder.svg
syft_rds/assets/svg/info.svg
syft_rds/assets/svg/request.svg
syft_rds/assets/svg/search.svg
syft_rds/assets/svg/table.svg
syft_rds/client/__init__.py
syft_rds/client/client_registry.py
syft_rds/client/connection.py
syft_rds/client/exceptions.py
syft_rds/client/local_store.py
syft_rds/client/rds_client.py
syft_rds/client/rpc.py
syft_rds/client/setup.py
syft_rds/client/utils.py
syft_rds/client/local_stores/__init__.py
syft_rds/client/local_stores/base.py
syft_rds/client/local_stores/custom_function.py
syft_rds/client/local_stores/job.py
syft_rds/client/local_stores/runtime.py
syft_rds/client/local_stores/user_code.py
syft_rds/client/local_stores/dataset/__init__.py
syft_rds/client/local_stores/dataset/constants.py
syft_rds/client/local_stores/dataset/store.py
syft_rds/client/local_stores/dataset/managers/__init__.py
syft_rds/client/local_stores/dataset/managers/files.py
syft_rds/client/local_stores/dataset/managers/path.py
syft_rds/client/local_stores/dataset/managers/schema.py
syft_rds/client/local_stores/dataset/managers/url.py
syft_rds/client/rds_clients/__init__.py
syft_rds/client/rds_clients/base.py
syft_rds/client/rds_clients/custom_function.py
syft_rds/client/rds_clients/dataset.py
syft_rds/client/rds_clients/job.py
syft_rds/client/rds_clients/runtime.py
syft_rds/client/rds_clients/user_code.py
syft_rds-0.5.0.dist-info/METADATA
syft_rds-0.5.0.dist-info/WHEEL
syft_rds-0.5.0.dist-info/entry_points.txt
syft_rds-0.5.0.dist-info/licenses/LICENSE
syft_rds-0.5.0.dist-info/RECORD
