Metadata-Version: 2.4
Name: syft-rds
Version: 0.5.0
Summary: Doing remote data science with SyftBox
License-File: LICENSE
Requires-Python: >=3.9
Requires-Dist: ipython>=8.18.1
Requires-Dist: jinja2>=3.1.6
Requires-Dist: loguru>=0.7.3
Requires-Dist: nh3>=0.3.1
Requires-Dist: pydantic[email]>=2.12.0
Requires-Dist: pyyaml>=6.0.3
Requires-Dist: rich<14.0.0,>=13.5.0
Requires-Dist: syft-event>=0.4.2
Requires-Dist: tomli>=2.0.1; python_version < '3.11'
Requires-Dist: typer<0.13.0,>=0.12.5
Requires-Dist: typing-extensions>=4.15.0
